[{"channel": "MSNBC", "recommended": [{"channel": "Saturday Night Live", "link": "https://www.youtube.com/watch?v=AdQl7SxOHek", "title": "It's a Wonderful Trump Cold Open - SNL"}], "up_next_link": "https://www.youtube.com/watch?v=8Njmvdjy5Q8"}, {"channel": "MSNBC", "link": "https://www.youtube.com/watch?v=8Njmvdjy5Q8", "recommended": [{"channel": "NBC News", "link": "https://www.youtube.com/watch?v=n1cpQNFJkGY", "title": "Examining Trump\u2019s Relationship With Rudy Giuliani | NBC News Now"}, {"channel": "Fox News", "link": "https://www.youtube.com/watch?v=8S96lcAYk_0", "title": "Whitaker: Lisa Page made calculated move to front run IG report"}, {"channel": "CBS News", "link": "https://www.youtube.com/watch?v=F-HPiqcmIns", "title": "Kamala Harris drops out of presidential race"}, {"channel": "MSNBC", "link": "https://www.youtube.com/watch?v=Q_UXsyZMEc4", "title": "Neal Katyal On The Case For Impeaching President Donald Trump | The Last Word | MSNBC"}, {"channel": "MSNBC", "link": "https://www.youtube.com/watch?v=nCOSslm97-4&t=9s", "title": "WAPO: Democrats Debating Whether To Expand Trump Articles Of Impeachment | The 11th Hour | MSNBC"}], "up_next_link": "https://www.youtube.com/watch?v=zH3huGiBcWA"}, {"channel": "MSNBC", "link": "https://www.youtube.com/watch?v=zH3huGiBcWA", "recommended": [{"channel": "Maclean's", "link": "https://www.youtube.com/watch?v=0-kjJEFihto", "title": "Donald Trump's egregious lies: a brief selection"}, {"channel": "CNN", "link": "https://www.youtube.com/watch?v=xRLQwebAeAc", "title": "Adam Schiff speaks after House Democrats release impeachment report"}, {"channel": "MSNBC", "link": "https://www.youtube.com/watch?v=ZGyaGL7AeHY", "title": "Steve Bullock Suspends Presidential Campaign | Morning Joe | MSNBC"}, {"channel": "Fox News", "link": "https://www.youtube.com/watch?v=EyK5h3WYKBo", "title": "Jordan: Democrats never admitted they were wrong on Russia"}, {"channel": "QuickTake by Bloomberg", "link": "https://www.youtube.com/watch?v=1GjaLRmBPBs", "title": "Legal Troubles Behind Trump's Florida Residency Change, New York Gov. Cuomo Says"}], "up_next_link": "https://www.youtube.com/watch?v=Q_UXsyZMEc4"}, {"channel": "MSNBC", "link": "https://www.youtube.com/watch?v=Q_UXsyZMEc4", "recommended": [{"channel": "MSNBC", "link": "https://www.youtube.com/watch?v=OlPsM306hXk", "title": "Transcripts Released As House Judiciary Cmte. Schedules Impeachment Hearing | The Last Word | MSNBC"}, {"channel": "Fox News", "link": "https://www.youtube.com/watch?v=b9IKiRMCBVs", "title": "Rep. Biggs: Lisa Page once engaged in FBI cabal, now playing the victim"}, {"channel": "Saturday Night Live", "link": "https://www.youtube.com/watch?v=LlyV-hvcFwA", "title": "Weekend Update on the Nunes Memo - SNL"}, {"channel": "CNN", "link": "https://www.youtube.com/watch?v=mnmHQ5Oe-tY", "title": "Trump and Macron clash during NATO summit meeting"}, {"channel": "CNN", "link": "https://www.youtube.com/watch?v=Y3c7rkWFo0Q", "title": "Trump and the GOP have a conspiracy theory on Ukraine"}], "up_next_link": "https://www.youtube.com/watch?v=b7u-9gVaOBA"}, {"channel": "MSNBC", "link": "https://www.youtube.com/watch?v=b7u-9gVaOBA", "recommended": [{"channel": "Fox News", "link": "https://www.youtube.com/watch?v=e6wU0qdMt2Y", "title": "Trump asks Macron if he will take back ISIS fighters"}, {"channel": "MSNBC", "link": "https://www.youtube.com/watch?v=2zBj75V1te8", "title": "Rudy Giuliani Speaks, Causes Trouble For President Donald Trump | The Last Word | MSNBC"}, {"channel": "CNN", "link": "https://www.youtube.com/watch?v=7zAgl6cm8Jw", "title": "Cooper skewers Trump's photoshopped image of himself"}, {"channel": "Fox News", "link": "https://www.youtube.com/watch?v=b9IKiRMCBVs", "title": "Rep. Biggs: Lisa Page once engaged in FBI cabal, now playing the victim"}, {"channel": "MSNBC", "link": "https://www.youtube.com/watch?v=5-wqJqGadZ8", "title": "'A Liar' And 'A Fanatic': Calls To Impeach AG Barr After Speech Attacking 'The Resistance' | MSNBC"}], "up_next_link": "https://www.youtube.com/watch?v=e_4lO3zjOVI"}, {"channel": "MSNBC", "link": "https://www.youtube.com/watch?v=e_4lO3zjOVI", "recommended": [{"channel": "Fox News", "link": "https://www.youtube.com/watch?v=ge_vdLNGIBA&t=9s", "title": "Newt Gingrich: Democrats have a 'very weak' impeachment case"}, {"channel": "MSNBC", "link": "https://www.youtube.com/watch?v=Uak9Y1v4S7E", "title": "Lawrence: Donald Trump Making 'Increasingly Incoherent' Russia Statements | The Last Word | MSNBC"}, {"channel": "MSNBC", "link": "https://www.youtube.com/watch?v=CCmKEqkfiOw&t=9s", "title": "Devin Nunes Now Implicated In Ukraine scandal | All In | MSNBC"}, {"channel": "MSNBC", "link": "https://www.youtube.com/watch?v=d0be4st8lGw", "title": "The Atlantic: Ruthless Quotas At Amazon Are Maiming Employees | Velshi & Ruhle | MSNBC"}, {"channel": "QuickTake by Bloomberg", "link": "https://www.youtube.com/watch?v=1GjaLRmBPBs", "title": "Legal Troubles Behind Trump's Florida Residency Change, New York Gov. Cuomo Says"}], "up_next_link": "https://www.youtube.com/watch?v=4mhjXIHL0tY"}, {"channel": "MSNBC", "link": "https://www.youtube.com/watch?v=4mhjXIHL0tY", "recommended": [{"channel": "Fox News", "link": "https://www.youtube.com/watch?v=wklWnfAlja0", "title": "GOP Rep.: Americans should be outraged at Dems' impeachment report"}, {"channel": "Saturday Night Live", "link": "https://www.youtube.com/watch?v=AiyZ92_JZxA", "title": "Morning Joe Michael Wolff Cold Open - SNL"}, {"channel": "MSNBC", "link": "https://www.youtube.com/watch?v=CCmKEqkfiOw&t=9s", "title": "Devin Nunes Now Implicated In Ukraine scandal | All In | MSNBC"}, {"channel": "MSNBC", "link": "https://www.youtube.com/watch?v=5SBg_T0TMJE", "title": "How Donald Trump\u2019s Bluff On House Subpoenas May Backfire | The Beat With Ari Melber | MSNBC"}, {"channel": "MSNBC", "link": "https://www.youtube.com/watch?v=SEJtM3xRz1U&t=9s", "title": "Bill Barr Couldn't Be More Destructive AG Than If Putin Picked Him | The 11th Hour | MSNBC"}], "up_next_link": "https://www.youtube.com/watch?v=66r6_ZqgBbU"}, {"channel": "MSNBC", "link": "https://www.youtube.com/watch?v=66r6_ZqgBbU", "recommended": [{"channel": "MSNBC", "link": "https://www.youtube.com/watch?v=Uak9Y1v4S7E", "title": "Lawrence: Donald Trump Making 'Increasingly Incoherent' Russia Statements | The Last Word | MSNBC"}, {"channel": "Fox News", "link": "https://www.youtube.com/watch?v=8S96lcAYk_0", "title": "Whitaker: Lisa Page made calculated move to front run IG report"}, {"channel": "MSNBC", "link": "https://www.youtube.com/watch?v=CVSXenFcPoo", "title": "Lawrence On \u2018The Clear And Present Danger Of Mark Esperanto\u2019 | The Last Word | MSNBC"}, {"channel": "The Talk", "link": "https://www.youtube.com/watch?v=AtzTReA0efA", "title": "The Talk - Sharon Osbourne on Gabrielle Union 'America's Got Talent' Firing"}, {"channel": "CNN", "link": "https://www.youtube.com/watch?v=lPIhpavOwXM", "title": "House Republicans defend Trump's actions in new report responding to impeachment inquiry"}], "up_next_link": "https://www.youtube.com/watch?v=s89WWllTVjA"}, {"channel": "MSNBC", "link": "https://www.youtube.com/watch?v=s89WWllTVjA", "recommended": [{"channel": "The View", "link": "https://www.youtube.com/watch?v=6sSMxjmDhG0", "title": "\"America's Got Talent\u201d a Toxic Work Environment? | The View"}, {"channel": "Fox Business", "link": "https://www.youtube.com/watch?v=hsaIBHdJbk8", "title": "Peloton sparks sexism outcry with new holiday ad"}, {"channel": "MSNBC", "link": "https://www.youtube.com/watch?v=3qdvQ1EjDrM", "title": "Prosecutors Seeking Info On Payments To Rudy Giuliani | Hardball | MSNBC"}, {"channel": "The Late Show with Stephen Colbert", "link": "https://www.youtube.com/watch?v=6Up-UCTPx_M", "title": "Trump Peddles Threadbare Conspiracy Theories In Rambling Call To \"Fox & Friends\""}, {"channel": "Fox News", "link": "https://www.youtube.com/watch?v=7wkeHwHrKOk", "title": "House Intel Democrats release impeachment report"}], "up_next_link": "https://www.youtube.com/watch?v=D96IHNWJTxg"}, {"channel": "MSNBC", "link": "https://www.youtube.com/watch?v=D96IHNWJTxg", "recommended": [{"channel": "Fox News", "link": "https://www.youtube.com/watch?v=b9IKiRMCBVs", "title": "Rep. Biggs: Lisa Page once engaged in FBI cabal, now playing the victim"}, {"channel": "Fox Business", "link": "https://www.youtube.com/watch?v=1Xx1FRORAm0", "title": "House Intel releases impeachment report"}, {"channel": "MSNBC", "link": "https://www.youtube.com/watch?v=Drohp_uhc3Y", "title": "Trump Kept Two Sets Of Books For Trump Tower | All In | MSNBC"}, {"channel": "Fox News", "link": "https://www.youtube.com/watch?v=Oj-uDd2Y4kE", "title": "Tucker: Impeachment has made Trump even stronger"}, {"channel": "MSNBC", "link": "https://www.youtube.com/watch?v=5Iecm6enA1g", "title": "Call Logs Between Rudy Giuliani, Budget Office Revealed In Impeachment Report | Katy Tur | MSNBC"}], "up_next_link": "https://www.youtube.com/watch?v=pByrX-HvlhM"}, {"channel": "MSNBC", "link": "https://www.youtube.com/watch?v=pByrX-HvlhM", "recommended": [{"channel": "Fox News", "link": "https://www.youtube.com/watch?v=b9IKiRMCBVs", "title": "Rep. Biggs: Lisa Page once engaged in FBI cabal, now playing the victim"}, {"channel": "MSNBC", "link": "https://www.youtube.com/watch?v=syaApNy6DP8", "title": "Amid Ukraine Controversy, Trump Seems To Be Standing By Giuliani... For Now | The 11th Hour | MSNBC"}, {"channel": "MSNBC", "link": "https://www.youtube.com/watch?v=5Iecm6enA1g", "title": "Call Logs Between Rudy Giuliani, Budget Office Revealed In Impeachment Report | Katy Tur | MSNBC"}, {"channel": "HoleVEVO", "link": "https://www.youtube.com/watch?v=O3dWBLoU--E", "title": "Hole - Celebrity Skin (Official Video)"}, {"channel": "MSNBC", "link": "https://www.youtube.com/watch?v=rTx-qFTWkhw", "title": "\"Death wish\": Trump co-author Says 'Self-Destructive' Trump Fuels Impeachment With Behavior"}], "up_next_link": "https://www.youtube.com/watch?v=Drohp_uhc3Y"}, {"channel": "MSNBC", "link": "https://www.youtube.com/watch?v=Drohp_uhc3Y", "recommended": [{"channel": "Fox Business", "link": "https://www.youtube.com/watch?v=S3-V4M0GOBc", "title": "December 15 tariff deadline on China still moving forward: Sources"}, {"channel": "MSNBC", "link": "https://www.youtube.com/watch?v=cUZyjC6IfJw", "title": "Donald Trump Ethics Chief Resigns Sooner Than Most | The Beat With Ari Melber | MSNBC"}, {"channel": "Late Night with Seth Meyers", "link": "https://www.youtube.com/watch?v=ApGvKDNEDFo", "title": "President Trump\u2019s Thanksgiving Proclamation"}, {"channel": "MSNBC", "link": "https://www.youtube.com/watch?v=4PGrSykifAM", "title": "House Committee Cites 'Pattern Of Abuse' At OMB Over Ukraine Aid | Rachel Maddow | MSNBC"}, {"channel": "Fox Business", "link": "https://www.youtube.com/watch?v=lXzM0IcCHQA", "title": "Trish Regan: Media shows its bias criticizing Trump\u2019s troop visit"}], "up_next_link": "https://www.youtube.com/watch?v=FK-aPDcplgY"}, {"channel": "MSNBC", "link": "https://www.youtube.com/watch?v=FK-aPDcplgY", "recommended": [{"channel": "Fox News", "link": "https://www.youtube.com/watch?v=GZcnrkuC13o", "title": "Doug Collins: Adam Schiff is the first person who needs to testify"}, {"channel": "CNN", "link": "https://www.youtube.com/watch?v=e_F5_S1A3zY", "title": "Jim Scuitto fact-checks Sen. John Kennedy's Ukraine election interference claims"}, {"channel": "MSNBC", "link": "https://www.youtube.com/watch?v=RXeQ6WZJaiE", "title": "AG Barr Questions Findings From IG Report | Morning Joe | MSNBC"}, {"channel": "Fox Business", "link": "https://www.youtube.com/watch?v=fxwYPuIiKOw", "title": "The US has the best economy in the world: JMP Securities president"}, {"channel": "CNN", "link": "https://www.youtube.com/watch?v=bVjhfaZfzJI", "title": "Trump slams Macron for insulting NATO while insulting NATO"}], "up_next_link": "https://www.youtube.com/watch?v=1PGyFAhWuOc"}, {"channel": "MSNBC", "link": "https://www.youtube.com/watch?v=1PGyFAhWuOc", "recommended": [{"channel": "MSNBC", "link": "https://www.youtube.com/watch?v=hm2fbKo7uXo", "title": "President Donald Trump Calls Impeachment Inquiry 'Bullshit' | Hardball | MSNBC"}, {"channel": "Fox Business", "link": "https://www.youtube.com/watch?v=hsaIBHdJbk8", "title": "Peloton sparks sexism outcry with new holiday ad"}, {"channel": "CNN", "link": "https://www.youtube.com/watch?v=V-h54uMQlqg", "title": "Ex-FBI lawyer Lisa Page targeted by Trump breaks silence"}, {"channel": "Late Night with Seth Meyers", "link": "https://www.youtube.com/watch?v=GgQPmj6pZL4", "title": "Poll Finds That Half of the Country Believes Trump Should Be Impeached"}, {"channel": "CNN", "link": "https://www.youtube.com/watch?v=bVjhfaZfzJI", "title": "Trump slams Macron for insulting NATO while insulting NATO"}], "up_next_link": "https://www.youtube.com/watch?v=syaApNy6DP8"}, {"channel": "MSNBC", "link": "https://www.youtube.com/watch?v=syaApNy6DP8", "recommended": [{"channel": "MSNBC", "link": "https://www.youtube.com/watch?v=5Iecm6enA1g", "title": "Call Logs Between Rudy Giuliani, Budget Office Revealed In Impeachment Report | Katy Tur | MSNBC"}, {"channel": "CNN", "link": "https://www.youtube.com/watch?v=bVjhfaZfzJI", "title": "Trump slams Macron for insulting NATO while insulting NATO"}, {"channel": "MSNBC", "link": "https://www.youtube.com/watch?v=fMj1uuL-6yc", "title": "Two Central Figures Face New Scrutiny In The Impeachment Inquiry | Deadline | MSNBC"}, {"channel": "CNN", "link": "https://www.youtube.com/watch?v=e_F5_S1A3zY", "title": "Jim Scuitto fact-checks Sen. John Kennedy's Ukraine election interference claims"}, {"channel": "MSNBC", "link": "https://www.youtube.com/watch?v=NMO9xjeoDNg", "title": "Ashley Parker On Rudy Giuliani's Fate: Trump Is Loyal Until He's Not | The 11th Hour | MSNBC"}], "up_next_link": "https://www.youtube.com/watch?v=n1cpQNFJkGY"}, {"channel": "NBC News", "link": "https://www.youtube.com/watch?v=n1cpQNFJkGY", "recommended": [{"channel": "Fox News", "link": "https://www.youtube.com/watch?v=piKfHqUc9v0", "title": "Sen. John Kennedy hits back at Hillary Clinton's Russia accusations"}, {"channel": "CNN", "link": "https://www.youtube.com/watch?v=bVjhfaZfzJI", "title": "Trump slams Macron for insulting NATO while insulting NATO"}, {"channel": "Late Night with Seth Meyers", "link": "https://www.youtube.com/watch?v=2S5PYP_TfK4", "title": "Trump Attacks Conway and McCain, Nunes Sues Twitter: A Closer Look"}, {"channel": "Fox Business", "link": "https://www.youtube.com/watch?v=1Xx1FRORAm0", "title": "House Intel releases impeachment report"}, {"channel": "MSNBC", "link": "https://www.youtube.com/watch?v=MT3_2tpPpQE", "title": "Top Diplomat Rips Trump Ukraine 'Scam' As Damning Texts Emerge | The Beat With Ari Melber | MSNBC"}], "up_next_link": "https://www.youtube.com/watch?v=NMO9xjeoDNg"}, {"channel": "MSNBC", "link": "https://www.youtube.com/watch?v=NMO9xjeoDNg", "recommended": [{"channel": "MSNBC", "link": "https://www.youtube.com/watch?v=93k9vI1WnF8", "title": "Ousted Navy Secretary Sounds Off After Trump Jumps Into SEAL Controversy | The 11th Hour | MSNBC"}, {"channel": "Fox News", "link": "https://www.youtube.com/watch?v=piKfHqUc9v0", "title": "Sen. John Kennedy hits back at Hillary Clinton's Russia accusations"}, {"channel": "MSNBC", "link": "https://www.youtube.com/watch?v=3LvAguqEGK0", "title": "Trump Tweets He Would 'Love' To Have Officials Testify In Impeachment Probe | Hallie Jackson | MSNBC"}, {"channel": "MSNBC", "link": "https://www.youtube.com/watch?v=5Iecm6enA1g", "title": "Call Logs Between Rudy Giuliani, Budget Office Revealed In Impeachment Report | Katy Tur | MSNBC"}, {"channel": "Fox News", "link": "https://www.youtube.com/watch?v=Cl-qk9uaefc", "title": "President George H.W. Bush\u2019s service dog Sully memorialized with statue"}], "up_next_link": "https://www.youtube.com/watch?v=HWkEBy9shhI"}, {"channel": "MSNBC", "link": "https://www.youtube.com/watch?v=HWkEBy9shhI", "recommended": [{"channel": "Fox Business", "link": "https://www.youtube.com/watch?v=Ife3nXDG7Ik", "title": "Judge rules ex-White House counsel McGahn must testify before Congress"}, {"channel": "MSNBC", "link": "https://www.youtube.com/watch?v=gGzMRBinOYo", "title": "House Judiciary Committee Announces Next Impeachment Hearing | Velshi & Ruhle | MSNBC"}, {"channel": "CNN", "link": "https://www.youtube.com/watch?v=xRLQwebAeAc", "title": "Adam Schiff speaks after House Democrats release impeachment report"}, {"channel": "MSNBC", "link": "https://www.youtube.com/watch?v=mgzTC8ih4JU", "title": "'Hard Evidence': Feds Subpoena Giuliani Business As Indicted Associate Hands Over Secret Tapes"}, {"channel": "MSNBC", "link": "https://www.youtube.com/watch?v=Y-bKMcBRMdo", "title": "Trump Slams Macron For 'Insulting' NATO Comments | Morning Joe | MSNBC"}], "up_next_link": "https://www.youtube.com/watch?v=4AqvztWmAgA"}, {"channel": "MSNBC", "link": "https://www.youtube.com/watch?v=4AqvztWmAgA", "recommended": [{"channel": "Fox News", "link": "https://www.youtube.com/watch?v=dmHnTmsQZaA", "title": "Peter Navarro on what Democrats are losing focus on"}, {"channel": "Saturday Night Live", "link": "https://www.youtube.com/watch?v=VDNQEplDHjA", "title": "Trump Impeachment Press Conference Cold Open - SNL"}, {"channel": "MSNBC", "link": "https://www.youtube.com/watch?v=STJVv0MdEZs", "title": "Melania Trump Loudly Booed At Opioid Summit In Baltimore | Craig Melvin | MSNBC"}, {"channel": "Fox Business", "link": "https://www.youtube.com/watch?v=Ife3nXDG7Ik", "title": "Judge rules ex-White House counsel McGahn must testify before Congress"}, {"channel": "MSNBC", "link": "https://www.youtube.com/watch?v=5Iecm6enA1g", "title": "Call Logs Between Rudy Giuliani, Budget Office Revealed In Impeachment Report | Katy Tur | MSNBC"}], "up_next_link": "https://www.youtube.com/watch?v=pxNI5AJdagc"}, {"channel": "MSNBC", "link": "https://www.youtube.com/watch?v=pxNI5AJdagc", "recommended": [{"channel": "MSNBC", "link": "https://www.youtube.com/watch?v=6n772IvKvRI", "title": "By The Numbers: Steve Kornacki Breaks Down Why Sen. Harris Dropped Out | Velshi & Ruhle | MSNBC"}, {"channel": "QuickTake by Bloomberg", "link": "https://www.youtube.com/watch?v=1GjaLRmBPBs", "title": "Legal Troubles Behind Trump's Florida Residency Change, New York Gov. Cuomo Says"}, {"channel": "MSNBC", "link": "https://www.youtube.com/watch?v=fMj1uuL-6yc", "title": "Two Central Figures Face New Scrutiny In The Impeachment Inquiry | Deadline | MSNBC"}, {"channel": "MSNBC", "link": "https://www.youtube.com/watch?v=5Iecm6enA1g", "title": "Call Logs Between Rudy Giuliani, Budget Office Revealed In Impeachment Report | Katy Tur | MSNBC"}, {"channel": "CNN", "link": "https://www.youtube.com/watch?v=e_F5_S1A3zY", "title": "Jim Scuitto fact-checks Sen. John Kennedy's Ukraine election interference claims"}], "up_next_link": "https://www.youtube.com/watch?v=r5R3AQiHdYg"}, {"channel": "Fox News", "link": "https://www.youtube.com/watch?v=r5R3AQiHdYg", "recommended": [{"channel": "Fox News", "link": "https://www.youtube.com/watch?v=NUqNKpjxPTE", "title": "Energy Secretary Rick Perry responds to Sondland's testimony"}, {"channel": "Fox News", "link": "https://www.youtube.com/watch?v=ehSf2q2gFv4", "title": "Is focus on impeachment backfiring for Democrats?"}, {"channel": "Fox Business", "link": "https://www.youtube.com/watch?v=9SsZVwonUHw", "title": "Second Schiff staffer tied to Burisma-backed think tank: Report"}, {"channel": "CNN", "link": "https://www.youtube.com/watch?v=3LZkR3hSepc", "title": "Giuliani backtracks after 'joking' that Trump might betray him"}, {"channel": "MSNBC", "link": "https://www.youtube.com/watch?v=6n772IvKvRI", "title": "By The Numbers: Steve Kornacki Breaks Down Why Sen. Harris Dropped Out | Velshi & Ruhle | MSNBC"}], "up_next_link": "https://www.youtube.com/watch?v=bC9ofwNz8SQ"}, {"channel": "Fox News", "link": "https://www.youtube.com/watch?v=bC9ofwNz8SQ", "recommended": [{"channel": "Fox News", "link": "https://www.youtube.com/watch?v=ehSf2q2gFv4", "title": "Is focus on impeachment backfiring for Democrats?"}, {"channel": "Fox Business", "link": "https://www.youtube.com/watch?v=vyWv1T3NXtM", "title": "Recent market selloff is 'noise', investors should stay calm: Economist"}, {"channel": "Fox News", "link": "https://www.youtube.com/watch?v=VlDfhJ_dpyw", "title": "Lara Logan reacts to Nunes' criticism of Dems, the media"}, {"channel": "Fox Business", "link": "https://www.youtube.com/watch?v=9SsZVwonUHw", "title": "Second Schiff staffer tied to Burisma-backed think tank: Report"}, {"channel": "MSNBC", "link": "https://www.youtube.com/watch?v=fMj1uuL-6yc", "title": "Two Central Figures Face New Scrutiny In The Impeachment Inquiry | Deadline | MSNBC"}], "up_next_link": "https://www.youtube.com/watch?v=xsSjIAjTaDU"}, {"channel": "Fox News", "link": "https://www.youtube.com/watch?v=xsSjIAjTaDU", "recommended": [{"channel": "Fox News", "link": "https://www.youtube.com/watch?v=_gNQS0duASo", "title": "Gowdy on whistleblower: Here's why 'anonymous sources' shouldn't count"}, {"channel": "Fox News", "link": "https://www.youtube.com/watch?v=ofEfSyI7ULo", "title": "China reacts to Trump signing two bills backing Hong Kong protests"}, {"channel": "Fox News", "link": "https://www.youtube.com/watch?v=IU4ImUfBX64", "title": "Andy Biggs expects 'feisty' impeachment hearings in House Judiciary"}, {"channel": "MSNBC", "link": "https://www.youtube.com/watch?v=6n772IvKvRI", "title": "By The Numbers: Steve Kornacki Breaks Down Why Sen. Harris Dropped Out | Velshi & Ruhle | MSNBC"}, {"channel": "Fox News", "link": "https://www.youtube.com/watch?v=4UMdc5nUd8U", "title": "Gaetz: Hunter Biden would be one of our top witnesses"}], "up_next_link": "https://www.youtube.com/watch?v=9SsZVwonUHw"}, {"channel": "Fox Business", "link": "https://www.youtube.com/watch?v=9SsZVwonUHw", "recommended": [{"channel": "The Heritage Foundation", "link": "https://www.youtube.com/watch?v=uNWUDQ1IYbg", "title": "Hans von Spakovsky: Horowitz Report Is Investigating Obama Admin's Potential \"Gross Abuse of Power\""}, {"channel": "Fox Business", "link": "https://www.youtube.com/watch?v=eSRMogajSew", "title": "Ken Cuccinelli fires back at O'Malley after confrontation in DC bar"}, {"channel": "MSNBC", "link": "https://www.youtube.com/watch?v=6OVKKKAaLtE", "title": "The Hits Keep Coming For Donald Trump And His Allies | Deadline | MSNBC"}, {"channel": "Fox Business", "link": "https://www.youtube.com/watch?v=a-0PfNuoZV8", "title": "Washington Post calls out Schiff over false whistleblower comments"}, {"channel": "FOX 10 Phoenix", "link": "https://www.youtube.com/watch?v=-PtrpWPxrYg", "title": "BURISMA ALERT: Devin Nunes DIGS into Hunter Biden controversy"}], "up_next_link": "https://www.youtube.com/watch?v=bk4u6CMurIU"}, {"channel": "Fox Business", "link": "https://www.youtube.com/watch?v=bk4u6CMurIU", "recommended": [{"channel": "MSNBC", "link": "https://www.youtube.com/watch?v=LD8aQ4iCeco", "title": "Trump Won't Leave Politics At Water's Edge In London | Morning Joe | MSNBC"}, {"channel": "POLITICO", "link": "https://www.youtube.com/watch?v=rwpX0Ax0XCA", "title": "Rep. Nunes and Lt. Col. Vindman have tense exchange over whistleblower | POLITICO"}, {"channel": "Fox Business", "link": "https://www.youtube.com/watch?v=h5wMvO7ZMNA", "title": "Trish Regan: Schiff says he doesn't know whistleblower, despite contradicting reports"}, {"channel": "Fox News", "link": "https://www.youtube.com/watch?v=Ldg76_Awp3A", "title": "How the DNC rigged the nomination for Hillary"}, {"channel": "Fox Business", "link": "https://www.youtube.com/watch?v=YESekOn9eC8", "title": "Ex-FBI agent who worked with Comey calls him 'unqualified'"}], "up_next_link": "https://www.youtube.com/watch?v=WEX-gcjRzBQ"}, {"channel": "Fox News", "link": "https://www.youtube.com/watch?v=WEX-gcjRzBQ", "recommended": [{"channel": "Fox News", "link": "https://www.youtube.com/watch?v=mw55Md9ej9c", "title": "Dem court filing suggests Trump impeachment probe began before Mueller report was submitted"}, {"channel": "Fox Business", "link": "https://www.youtube.com/watch?v=vyWv1T3NXtM", "title": "Recent market selloff is 'noise', investors should stay calm: Economist"}, {"channel": "MSNBC", "link": "https://www.youtube.com/watch?v=fMj1uuL-6yc", "title": "Two Central Figures Face New Scrutiny In The Impeachment Inquiry | Deadline | MSNBC"}, {"channel": "Fox News", "link": "https://www.youtube.com/watch?v=UIKfJ_6PuoI", "title": "Emails suggest Huma Abedin was careless with classified info"}, {"channel": "Fox News", "link": "https://www.youtube.com/watch?v=0QxKM5-XbP8", "title": "Hilton: British government remains shamefully silent on Hong Kong"}], "up_next_link": "https://www.youtube.com/watch?v=eSRMogajSew"}]
